binary_repr/__init__.py
binary_repr/pyfuncs.py
binary_repr-0.1.0.dist-info/DESCRIPTION.rst
binary_repr-0.1.0.dist-info/METADATA
binary_repr-0.1.0.dist-info/RECORD
binary_repr-0.1.0.dist-info/WHEEL
binary_repr-0.1.0.dist-info/metadata.json
binary_repr-0.1.0.dist-info/top_level.txt
