Metadata-Version: 2.0
Name: binary-repr
Version: 0.1.0
Summary: Converts integers to binary representation.
Home-page: https://github.com/rolando/binary-repr
Author: Rolando Espinoza
Author-email: rolando at rmax.io
License: MIT
Keywords: binary representation
Platform: UNKNOWN
Classifier: Development Status :: 2 - Pre-Alpha
Classifier: Intended Audience :: Developers
Classifier: License :: OSI Approved :: MIT License
Classifier: Natural Language :: English
Classifier: Programming Language :: Python :: 2
Classifier: Programming Language :: Python :: 2.7
Classifier: Programming Language :: Python :: 3
Classifier: Programming Language :: Python :: 3.5
